feature_selection/__init__.py
feature_selection/algorithms.py
feature_selection/hybrid_algorithms.py
feature_selection/machine_learning_algorithms.py
feature_selectionpy-0.0.4.dist-info/LICENSE.txt
feature_selectionpy-0.0.4.dist-info/METADATA
feature_selectionpy-0.0.4.dist-info/WHEEL
feature_selectionpy-0.0.4.dist-info/top_level.txt
feature_selectionpy-0.0.4.dist-info/RECORD
