Metadata-Version: 2.1
Name: feature-selectionpy
Version: 0.0.4
Summary: A Python feature selection project
Home-page: https://github.com/chandraveshchaudhari/browser-automationpy
Author: Chandravesh Chaudhari
Author-email: chandraveshchaudhari@example.com
Project-URL: Bug Tracker, https://github.com/chandraveshchaudhari/hybrid-feature-selection/issues
Project-URL: Bug Reports, https://github.com/chandraveshchaudhari/hybrid-feature-selection/issues
Project-URL: Say Thanks!, https://saythanks.io/to/chandraveshchaudhari
Project-URL: Source, https://github.com/chandraveshchaudhari/hybrid-feature-selection/
Keywords: browser,automation,selenium,testing,data mining
Classifier: Development Status :: 4 - Beta
Classifier: Operating System :: OS Independent
Classifier: Intended Audience :: Developers
Classifier: Intended Audience :: End Users/Desktop
Classifier: Topic :: Software Development :: Build Tools
Classifier: Topic :: Internet :: WWW/HTTP :: Browsers
Classifier: License :: OSI Approved :: MIT License
Classifier: Programming Language :: Python :: 3
Classifier: Programming Language :: Python :: 3.6
Classifier: Programming Language :: Python :: 3.7
Classifier: Programming Language :: Python :: 3.8
Classifier: Programming Language :: Python :: 3.9
Requires-Python: >=3.6, <4
License-File: LICENSE.txt
Requires-Dist: keras (==2.11.0)
Requires-Dist: mlxtend (==0.21.0)
Requires-Dist: pandas (==1.5.2)
Requires-Dist: ReliefF (==0.1.2)
Requires-Dist: scipy (==1.9.3)
Requires-Dist: shap (==0.41.0)
Requires-Dist: scikit-learn
Requires-Dist: skrebate (==0.62)
Requires-Dist: systematic-reviewpy (==0.0.1)
Requires-Dist: tensorboard (==2.11.0)
Requires-Dist: tensorboard-data-server (==0.6.1)
Requires-Dist: tensorboard-plugin-wit (==1.8.1)
Requires-Dist: tensorflow (==2.11.0)
Requires-Dist: tensorflow-estimator (==2.11.0)
Requires-Dist: tensorflow-io-gcs-filesystem (==0.29.0)
Requires-Dist: xgboost (==1.7.2)
